open_weather_api_JG/__init__.py
open_weather_api_JG/getweatherdata.py
open_weather_api_JG/getweatherdata_test.py
open_weather_api_JG/owm_key.py
open_weather_api_jg-0.1.2.dist-info/METADATA
open_weather_api_jg-0.1.2.dist-info/WHEEL
open_weather_api_jg-0.1.2.dist-info/RECORD
